txs/__init__.py
txs/_version.py
txs/azav.py
txs/common.py
txs/corr.py
txs/datared.py
txs/datasets.py
txs/heating.py
txs/live.py
txs/plot.py
txs/utils.py
txs/xes.py
txs/analysis/__init__.py
txs/analysis/plot.py
txs/analysis/svd.py
txs/analysis/utils.py
txs/app/MainWindow.py
txs/app/PlotBase.py
txs/app/PlotHeatmap.py
txs/app/ProcessWorker.py
txs/app/__init__.py
txs/app/__main__.py
txs/app/actions.py
txs/app/mainwindow.ui
txs/app/plot.py
txs/app/utils.py
txs/app/widgets.py
txs/app/tests/test_ProcessWorker.py
txs/detectors/__init__.py
txs/detectors/jungfrau.py
txs/tests/conftest.py
txs/tests/test_azav.py
txs/tests/test_corr.py
txs/tests/test_datared.py
txs/tests/test_datasets.py
txs/tests/test_utils.py
pytxs-0.0.1.dist-info/LICENSE.rst
pytxs-0.0.1.dist-info/METADATA
pytxs-0.0.1.dist-info/WHEEL
pytxs-0.0.1.dist-info/entry_points.txt
pytxs-0.0.1.dist-info/top_level.txt
pytxs-0.0.1.dist-info/RECORD
