Metadata-Version: 2.1
Name: pytxs
Version: 0.0.1
Summary: time-resolved x-ray scattering
Author-email: Matteo Levantino <matteo.levantino@esrf.fr>
License: MIT
Project-URL: Homepage, https://gitlab.esrf.fr/levantin/txs
Classifier: Intended Audience :: Science/Research
Classifier: Topic :: Scientific/Engineering :: Physics
Classifier: License :: OSI Approved :: MIT License
Classifier: Programming Language :: Python :: 3
Requires-Python: >=3.8
License-File: LICENSE.rst
Requires-Dist: numpy >=1.10
Requires-Dist: h5py >3.0
Requires-Dist: tqdm
Requires-Dist: fabio
Requires-Dist: pyFAI
Requires-Dist: xraydb >=4.3.4
Requires-Dist: datastorage
Provides-Extra: gui
Requires-Dist: PyQt5 ; extra == 'gui'
Requires-Dist: matplotlib ; extra == 'gui'
Requires-Dist: silx ; extra == 'gui'
